cedarkit/comp/__init__.py
cedarkit/comp/_version.py
cedarkit/comp/smooth.py
cedarkit/comp/util.py
cedarkit_comp-2024.4.0.dist-info/LICENSE
cedarkit_comp-2024.4.0.dist-info/METADATA
cedarkit_comp-2024.4.0.dist-info/WHEEL
cedarkit_comp-2024.4.0.dist-info/top_level.txt
cedarkit_comp-2024.4.0.dist-info/RECORD
